{
    "name": "SomeDescriptiveNameForThisEnvironment",
    "prov": "OnPrem",
    "tenant": "Sometenant",
    "application": "MyApp",
    "environment": {
        "name": "MyApp_dev",
        "description": "",
        "etype": "PRD",
        "cloudprovider": "OnPrem",
        "region": "primary",
        "availability_zone": "Pod1",
        "eversion": "1",
        "estatus": "Operational",
        "created": "2023-01-05T00:00:00",
        "updated": "2023-01-05T00:00:00",
        "last_change": "Someuser",
        "centercode": "0123456789",
        "change": "LDAP group name of system role permitted to Change/Update/Delete",
        "view": "LDAP group name of system role permitted to Read",
        "management-r": "LDAP group name of system role linked in IAM to operations team (Management-Responsible)",
        "management-a": "LDAP group name of system role linked in IAM to tactical operations team (Management-Accountable)",
        "management-i": "LDAP group name of system role linked in IAM to owner (Management-Inform)",
        "developer": "LDAP group name of system role linked in IAM to development team (Management-Supporting)"
    },
    "compartments": {
        "PA001": {
            "name": "pa1", 
            "description": "",
            "ctype": "PA",
            "environment": "MyApp_dev",
            "vdc": "",
            "cversion": "1",
            "cstatus": "Operational",
            "created": "2023-01-05T00:00:00",
            "updated": "2023-01-05T00:00:00",
            "last_change": "Someuser",
            "centercode": "0123456789",
            "change": "LDAP group name of system role permitted to Change/Update/Delete",
            "view": "LDAP group name of system role permitted to Read",
            "management-r": "LDAP group name of system role linked in IAM to operations team (Management-Responsible)",
            "management-a": "LDAP group name of system role linked in IAM to tactical operations team (Management-Accountable)",
            "management-i": "LDAP group name of system role linked in IAM to owner (Management-Inform)",
            "developer": "LDAP group name of system role linked in IAM to development team (Management-Supporting)",
            "numofservers": 3,
            "addressing": "IPv4"
        },
        "PA002": {
            "name": "pa2", 
            "description": "",
            "ctype": "PA",
            "environment": "MyApp_dev",
            "vdc": "",
            "cversion": "1",
            "cstatus": "Operational",
            "created": "2023-01-05T00:00:00",
            "updated": "2023-01-05T00:00:00",
            "last_change": "Someuser",
            "centercode": "0123456789",
            "change": "LDAP group name of system role permitted to Change/Update/Delete",
            "view": "LDAP group name of system role permitted to Read",
            "management-r": "LDAP group name of system role linked in IAM to operations team (Management-Responsible)",
            "management-a": "LDAP group name of system role linked in IAM to tactical operations team (Management-Accountable)",
            "management-i": "LDAP group name of system role linked in IAM to owner (Management-Inform)",
            "developer": "LDAP group name of system role linked in IAM to development team (Management-Supporting)",
            "numofservers": 3,
            "addressing": "IPv4"
        }
    },
    "servers": {
        "PA001SRV001": {
            "name": "PA001SRV001",
            "description": "Something",
            "compartment": "PA001",
            "size": "Small",
            "serverrole": "Web server",
            "OS": "RHEL8",
            "version": 1,
            "created": "2023-01-05T00:00:00",
            "updated": "2023-01-05T00:00:00",
            "last_change": "Someuser",
            "Centercode": "0123456789",
            "Change": "LDAP group name of system role permitted to Change/Update/Delete",
            "View": "LDAP group name of system role permitted to Read",
            "Management-r": "LDAP group name of system role linked in IAM to operations team (Management-Responsible)",
            "Management-a": "LDAP group name of system role linked in IAM to tactical operations team (Management-Accountable)",
            "Management-i": "LDAP group name of system role linked in IAM to owner (Management-Inform)",
            "Developer": "LDAP group name of system role linked in IAM to development team (Management-Supporting)"
        },
        "PA001SRV002": {
            "name": "PA001SRV002",
            "description": "Something",
            "compartment": "PA001",
            "size": "Small",
            "serverrole": "Web server",
            "OS": "Windows Server 2022",
            "version": 1,
            "created": "2023-01-05T00:00:00",
            "updated": "2023-01-05T00:00:00",
            "last_change": "Someuser",
            "Centercode": "0123456789",
            "Change": "LDAP group name of system role permitted to Change/Update/Delete",
            "View": "LDAP group name of system role permitted to Read",
            "Management-r": "LDAP group name of system role linked in IAM to operations team (Management-Responsible)",
            "Management-a": "LDAP group name of system role linked in IAM to tactical operations team (Management-Accountable)",
            "Management-i": "LDAP group name of system role linked in IAM to owner (Management-Inform)",
            "Developer": "LDAP group name of system role linked in IAM to development team (Management-Supporting)"
        },
        "PA001SRV003": {
            "name": "PA001SRV003",
            "description": "Something",
            "compartment": "PA001",
            "size": "Small",
            "serverrole": "Web server",
            "OS": "Windows Server 2022",
            "version": 1,
            "created": "2023-01-05T00:00:00",
            "updated": "2023-01-05T00:00:00",
            "last_change": "Someuser",
            "Centercode": "0123456789",
            "Change": "LDAP group name of system role permitted to Change/Update/Delete",
            "View": "LDAP group name of system role permitted to Read",
            "Management-r": "LDAP group name of system role linked in IAM to operations team (Management-Responsible)",
            "Management-a": "LDAP group name of system role linked in IAM to tactical operations team (Management-Accountable)",
            "Management-i": "LDAP group name of system role linked in IAM to owner (Management-Inform)",
            "Developer": "LDAP group name of system role linked in IAM to development team (Management-Supporting)"
        },
        "SHD001SRV001": {
            "name": "SHD001SRV001",
            "description": "Something",
            "compartment": "SHD001",
            "size": "Small",
            "serverrole": "Web server",
            "OS": "Windows Server 2022",
            "version": 1,
            "created": "2023-01-05T00:00:00",
            "updated": "2023-01-05T00:00:00",
            "last_change": "Someuser",
            "Centercode": "0123456789",
            "Change": "LDAP group name of system role permitted to Change/Update/Delete",
            "View": "LDAP group name of system role permitted to Read",
            "Management-r": "LDAP group name of system role linked in IAM to operations team (Management-Responsible)",
            "Management-a": "LDAP group name of system role linked in IAM to tactical operations team (Management-Accountable)",
            "Management-i": "LDAP group name of system role linked in IAM to owner (Management-Inform)",
            "Developer": "LDAP group name of system role linked in IAM to development team (Management-Supporting)"
        },
        "SHD002SRV001": {
            "name": "SHD002SRV001",
            "description": "Something",
            "compartment": "SHD002",
            "size": "Small",
            "serverrole": "Web server",
            "OS": "Windows Server 2022",
            "version": 1,
            "created": "2023-01-05T00:00:00",
            "updated": "2023-01-05T00:00:00",
            "last_change": "Someuser",
            "Centercode": "0123456789",
            "Change": "LDAP group name of system role permitted to Change/Update/Delete",
            "View": "LDAP group name of system role permitted to Read",
            "Management-r": "LDAP group name of system role linked in IAM to operations team (Management-Responsible)",
            "Management-a": "LDAP group name of system role linked in IAM to tactical operations team (Management-Accountable)",
            "Management-i": "LDAP group name of system role linked in IAM to owner (Management-Inform)",
            "Developer": "LDAP group name of system role linked in IAM to development team (Management-Supporting)"
        },
        "SHD002SRV002": {
            "name": "SHD002SRV002",
            "description": "Something",
            "compartment": "SHD002",
            "size": "Small",
            "serverrole": "Web server",
            "OS": "Windows Server 2022",
            "version": 1,
            "created": "2023-01-05T00:00:00",
            "updated": "2023-01-05T00:00:00",
            "last_change": "Someuser",
            "Centercode": "0123456789",
            "Change": "LDAP group name of system role permitted to Change/Update/Delete",
            "View": "LDAP group name of system role permitted to Read",
            "Management-r": "LDAP group name of system role linked in IAM to operations team (Management-Responsible)",
            "Management-a": "LDAP group name of system role linked in IAM to tactical operations team (Management-Accountable)",
            "Management-i": "LDAP group name of system role linked in IAM to owner (Management-Inform)",
            "Developer": "LDAP group name of system role linked in IAM to development team (Management-Supporting)"
        }
    },
    "conduits": {
        "TRAPP001": {
            "name": "TRAPP001",
            "description": "Something",
            "f-type": "TRAPP",
            "source": {},
            "destination": {},
            "version": 1,
            "created": "2023-01-05T00:00:00",
            "updated": "2023-01-05T00:00:00",
            "last_change": "Someuser",
            "Centercode": "0123456789",
            "Change": "LDAP group name of system role permitted to Change/Update/Delete",
            "View": "LDAP group name of system role permitted to Read",
            "Management-r": "LDAP group name of system role linked in IAM to operations team (Management-Responsible)",
            "Management-a": "LDAP group name of system role linked in IAM to tactical operations team (Management-Accountable)",
            "Management-i": "LDAP group name of system role linked in IAM to owner (Management-Inform)",
            "Developer": "LDAP group name of system role linked in IAM to development team (Management-Supporting)"
        }
    },
    "databases": {}
}
